dm_aiomysql/__init__.py
dm_aiomysql/aiomysql_client.py
dm_aiomysql/mysql_client.py
dm_aiomysql-0.1.5.dist-info/METADATA
dm_aiomysql-0.1.5.dist-info/WHEEL
dm_aiomysql-0.1.5.dist-info/top_level.txt
dm_aiomysql-0.1.5.dist-info/RECORD
