Metadata-Version: 2.4
Name: dm-aiomysql
Version: 0.1.5
Summary: This is my custom aiomysql client
Home-page: https://pypi.org/project/dm-aiomysql
Author: dimka4621
Author-email: mismartconfig@gmail.com
Project-URL: GitHub, https://github.com/MykhLibs/dm-aiomysql
Keywords: dm aiomysql
Classifier: Programming Language :: Python :: 3.8
Classifier: License :: OSI Approved :: MIT License
Classifier: Operating System :: OS Independent
Requires-Python: >=3.8
Requires-Dist: dm-logger~=0.6.2
Requires-Dist: python-dotenv>=1.0.0
Requires-Dist: mysql-connector-python<10.0.0,>=9.0.0
Dynamic: author
Dynamic: author-email
Dynamic: classifier
Dynamic: description
Dynamic: description-content-type
Dynamic: home-page
Dynamic: keywords
Dynamic: project-url
Dynamic: requires-dist
Dynamic: requires-python
Dynamic: summary
